{
    "name": "ListaPrecio",
    "fields": [
        {
            "fieldName": "nombre",
            "fieldType": "String"
        },
        {
            "fieldName": "porcentage",
            "fieldType": "BigDecimal"
        }
    ],
    "relationships": [],
    "changelogDate": "20181017191606",
    "javadoc": "ListaPrecio entity.\nesta entidad se usaria para aumentar\no disminuir precios globalmente\n@author The JHipster team.",
    "entityTableName": "lista_precio",
    "dto": "mapstruct",
    "pagination": "no",
    "service": "serviceImpl",
    "jpaMetamodelFiltering": false,
    "fluentMethods": true,
    "clientRootFolder": "",
    "applications": "*",
    "angularJSSuffix": "queenBeer"
}